kaos/__init__.py
kaos/_current.py
kaos/local.py
kaos/path.py
kaos/py.typed
kaos/ssh.py
pykaos-0.6.0.dist-info/WHEEL
pykaos-0.6.0.dist-info/METADATA
pykaos-0.6.0.dist-info/RECORD
