Metadata-Version: 2.3
Name: pykaos
Version: 0.6.0
Summary: 
Requires-Dist: aiofiles>=24.0,<26.0
Requires-Dist: asyncssh==2.21.1
Requires-Python: >=3.12
